pyuu/common/__init__.py
pyuu/env/__init__.py
pyuu.env-0.0.0.dist-info/METADATA
pyuu.env-0.0.0.dist-info/WHEEL
pyuu.env-0.0.0.dist-info/top_level.txt
pyuu.env-0.0.0.dist-info/RECORD
